xasdesgrambot/__init__.py
xasdesgrambot/bot.py
XasdesGramBot-0.3.dist-info/METADATA
XasdesGramBot-0.3.dist-info/WHEEL
XasdesGramBot-0.3.dist-info/top_level.txt
XasdesGramBot-0.3.dist-info/RECORD
